datosgobes/__init__.py
datosgobes/data_download.py
datosgobes/manager.py
datosgobes/opendataset.py
datosgobes-0.1.2.dist-info/licenses/LICENSE
datosgobes-0.1.2.dist-info/METADATA
datosgobes-0.1.2.dist-info/WHEEL
datosgobes-0.1.2.dist-info/top_level.txt
datosgobes-0.1.2.dist-info/RECORD
