Metadata-Version: 2.4
Name: datosgobes
Version: 0.1.2
Summary: Python package to access Spanish Government Open Data from the datos.gob.es API
Home-page: https://github.com/jvaleroliet/datosgobes
Author: Juan Valero
Author-email: olietvalero@gmail.com
License: MIT
Requires-Python: >=3.9
License-File: LICENSE
Requires-Dist: pandas>=2.2.0
Requires-Dist: requests>=2.31.0
Requires-Dist: numpy==1.26.4
Dynamic: author
Dynamic: author-email
Dynamic: home-page
Dynamic: license
Dynamic: license-file
Dynamic: requires-dist
Dynamic: requires-python
Dynamic: summary
